{"credit":"Made with Blockbench","texture_size":[128,128],"textures":{"3":"custom/skyblock/villager_statue_heroic","particle":"custom/skyblock/villager_statue_heroic"},"elements":[{"name":"body","from":[3,-12,6.25],"to":[13,11,13.75],"rotation":{"angle":0,"axis":"y","origin":[8,-19,10]},"faces":{"north":{"uv":[0.875,3.5,2.125,6.375],"texture":"#3"},"east":{"uv":[0,3.5,0.875,6.375],"texture":"#3"},"south":{"uv":[3,3.5,4.25,6.375],"texture":"#3"},"west":{"uv":[2.125,3.5,3,6.375],"texture":"#3"},"up":{"uv":[2.125,3.5,0.875,2.625],"texture":"#3"},"down":{"uv":[3.375,2.625,2.125,3.5],"texture":"#3"}}},{"name":"helmet","from":[2.998,12,7],"to":[12.998,22,17],"rotation":{"angle":22.5,"axis":"x","origin":[7.9875,17.9375,7.375]},"faces":{"north":{"uv":[5.5,3.875,6.75,5.125],"texture":"#3"},"east":{"uv":[4.25,3.875,5.5,5.125],"texture":"#3"},"south":{"uv":[8,3.875,9.25,5.125],"texture":"#3"},"west":{"uv":[6.75,3.875,8,5.125],"texture":"#3"},"up":{"uv":[6.75,3.875,5.5,2.625],"texture":"#3"},"down":{"uv":[8,2.625,6.75,3.875],"texture":"#3"}}},{"name":"helmet","from":[2.5,8.6875,11.8125],"to":[13.5,19.6875,15.8125],"rotation":{"angle":-45,"axis":"x","origin":[7.9875,17.9375,7.375]},"faces":{"north":{"uv":[4.75,5.625,6.125,7],"texture":"#3"},"east":{"uv":[4.25,5.625,4.75,7],"texture":"#3"},"south":{"uv":[6.625,5.625,8,7],"texture":"#3"},"west":{"uv":[6.125,5.625,6.625,7],"texture":"#3"},"up":{"uv":[6.125,5.625,4.75,5.125],"texture":"#3"},"down":{"uv":[7.5,5.125,6.125,5.625],"texture":"#3"}}},{"name":"brim","from":[-2.125,20.92388,-1.75768],"to":[18.075,22.42388,18.49232],"rotation":{"angle":45,"axis":"x","origin":[7.9875,16.9375,7.375]},"faces":{"north":{"uv":[2.5,2.5,5,2.625],"texture":"#3"},"east":{"uv":[0,2.5,2.5,2.625],"texture":"#3"},"south":{"uv":[7.5,2.5,10,2.625],"texture":"#3"},"west":{"uv":[5,2.5,7.5,2.625],"texture":"#3"},"up":{"uv":[5,2.5,2.5,0],"texture":"#3"},"down":{"uv":[7.5,0,5,2.5],"texture":"#3"}}},{"name":"nose","from":[6.5,10.75,5.125],"to":[9.5,15.75,8.125],"rotation":{"angle":22.5,"axis":"x","origin":[7.9875,17.9375,7.375]},"faces":{"north":{"uv":[7.875,1.625,8.25,2.25],"texture":"#3"},"east":{"uv":[7.5,1.625,7.875,2.25],"texture":"#3"},"south":{"uv":[8.625,1.625,9,2.25],"texture":"#3"},"west":{"uv":[8.25,1.625,8.625,2.25],"texture":"#3"},"up":{"uv":[8.25,1.625,7.875,1.25],"texture":"#3"},"down":{"uv":[8.625,1.25,8.25,1.625],"texture":"#3"}}},{"name":"arms","from":[-2,7.86396,9.25736],"to":[3,17.86396,14.25736],"rotation":{"angle":-22.5,"axis":"x","origin":[0.5,8.33579,11.05025]},"faces":{"north":{"uv":[5.625,7.625,6.25,8.875],"texture":"#3"},"east":{"uv":[5,7.625,5.625,8.875],"texture":"#3"},"south":{"uv":[6.875,7.625,7.5,8.875],"texture":"#3"},"west":{"uv":[6.25,7.625,6.875,8.875],"texture":"#3"},"up":{"uv":[6.25,7.625,5.625,7],"texture":"#3"},"down":{"uv":[6.875,7,6.25,7.625],"texture":"#3"}}},{"name":"arms","from":[-2,17.86396,9.25736],"to":[3,22.86396,14.25736],"rotation":{"angle":-22.5,"axis":"x","origin":[0.5,8.33579,11.05025]},"faces":{"north":{"uv":[8.125,0.625,8.75,1.25],"texture":"#3"},"east":{"uv":[7.5,0.625,8.125,1.25],"texture":"#3"},"south":{"uv":[9.375,0.625,10,1.25],"texture":"#3"},"west":{"uv":[8.75,0.625,9.375,1.25],"texture":"#3"},"up":{"uv":[8.75,0.625,8.125,0],"texture":"#3"},"down":{"uv":[9.375,0,8.75,0.625],"texture":"#3"}}},{"name":"arms","from":[13,-3.13604,7.25736],"to":[18,6.86396,12.25736],"rotation":{"angle":-22.5,"axis":"x","origin":[0.5,8.33579,11.05025]},"faces":{"north":{"uv":[3.125,7.625,3.75,8.875],"texture":"#3"},"east":{"uv":[2.5,7.625,3.125,8.875],"texture":"#3"},"south":{"uv":[4.375,7.625,5,8.875],"texture":"#3"},"west":{"uv":[3.75,7.625,4.375,8.875],"texture":"#3"},"up":{"uv":[3.75,7.625,3.125,7],"texture":"#3"},"down":{"uv":[4.375,7,3.75,7.625],"texture":"#3"}}},{"name":"arms","from":[13,6.86396,7.25736],"to":[18,11.86396,12.25736],"rotation":{"angle":-22.5,"axis":"x","origin":[0.5,8.33579,11.05025]},"faces":{"north":{"uv":[8,7,8.625,7.625],"texture":"#3"},"east":{"uv":[7.375,7,8,7.625],"texture":"#3"},"south":{"uv":[9.25,7,9.875,7.625],"texture":"#3"},"west":{"uv":[8.625,7,9.25,7.625],"texture":"#3"},"up":{"uv":[8.625,7,8,6.375],"texture":"#3"},"down":{"uv":[9.25,6.375,8.625,7],"texture":"#3"}}},{"name":"leg0","from":[3.002,-16,7.5],"to":[8.002,-5,12.5],"rotation":{"angle":0,"axis":"y","origin":[8,-19,10]},"faces":{"north":{"uv":[0.625,7,1.25,8.375],"texture":"#3"},"east":{"uv":[0,7,0.625,8.375],"texture":"#3"},"south":{"uv":[1.875,7,2.5,8.375],"texture":"#3"},"west":{"uv":[1.25,7,1.875,8.375],"texture":"#3"},"up":{"uv":[1.25,7,0.625,6.375],"texture":"#3"},"down":{"uv":[1.875,6.375,1.25,7],"texture":"#3"}}},{"name":"leg1","from":[7.998,-16,7.5],"to":[12.998,-5,12.5],"rotation":{"angle":0,"axis":"y","origin":[8,-19,10]},"faces":{"north":{"uv":[0.625,0.625,1.25,2],"texture":"#3"},"east":{"uv":[0,0.625,0.625,2],"texture":"#3"},"south":{"uv":[1.875,0.625,2.5,2],"texture":"#3"},"west":{"uv":[1.25,0.625,1.875,2],"texture":"#3"},"up":{"uv":[1.25,0.625,0.625,0],"texture":"#3"},"down":{"uv":[1.875,0,1.25,0.625],"texture":"#3"}}}],"display":{"thirdperson_righthand":{"rotation":[0,45,0],"translation":[-1.5,0,0],"scale":[0.3,0.3,0.3]},"thirdperson_lefthand":{"rotation":[0,45,0],"translation":[-1.5,0,0],"scale":[0.3,0.3,0.3]},"firstperson_righthand":{"scale":[0.55,0.55,0.55]},"firstperson_lefthand":{"scale":[0.55,0.55,0.55]},"ground":{"rotation":[90,0,0],"translation":[0,2.25,0],"scale":[0.5,0.5,0.5]},"gui":{"rotation":[22.5,135,0],"scale":[0.55,0.55,0.55]},"head":{"translation":[0,0.5,0.25],"scale":[1.24,1.24,1.24]},"fixed":{"rotation":[-90,-90,0],"translation":[4.5,0,-54],"scale":[2.29,2.29,2.29]}},"groups":[{"name":"body","origin":[0,0,0],"color":0,"children":[0,{"name":"head","origin":[0,24,0],"color":0,"children":[{"name":"helmet","origin":[0,24,0],"color":0,"children":[1,2]},{"name":"brim","origin":[0,24,0],"rotation":[90,0,0],"color":0,"children":[3]},{"name":"nose","origin":[0,26,0],"color":0,"children":[4]}]},{"name":"arms","origin":[0,22,0],"rotation":[45,0,0],"color":0,"children":[{"name":"group","origin":[16,23.75,0],"color":0,"children":[5,6]},{"name":"group","origin":[16,23.75,0],"color":0,"children":[7,8]}]},{"name":"RightLeg","origin":[2,12,0],"color":0,"children":[9]},{"name":"LeftLeg","origin":[-2,12,0],"color":0,"children":[10]}]}]}